hypergen/__init__.py
hypergen/apps.py
hypergen/context.py
hypergen/hypergen.py
hypergen/imports.py
hypergen/liveview.py
hypergen/template.py
hypergen/ultragen.pxd
hypergen/ultragen.pyx
hypergen/websocket.py
hypergen/plugins/__init__.py
hypergen/plugins/alertify.py
hypergen/plugins/appstate.py
hypergen/static/hypergen/dist/hypergen.js
hypergen/templatetags/__init__.py
hypergen/templatetags/hypergen.py
django_hypergen-1.5.5.dist-info/LICENSE
django_hypergen-1.5.5.dist-info/METADATA
django_hypergen-1.5.5.dist-info/WHEEL
django_hypergen-1.5.5.dist-info/top_level.txt
django_hypergen-1.5.5.dist-info/RECORD
