Metadata-Version: 2.1
Name: django-hypergen
Version: 1.5.5
Summary: Live view for django and templates in pure python
Home-page: https://github.com/runekaagaard/django-hypergen
Author: Rune Kaagaard & Jeppe Tuxen
Author-email: rumi.kg@gmail.com
Project-URL: Bug Tracker, https://github.com/runekaagaard/django-hypergen/issues
Classifier: Programming Language :: Python :: 3
Classifier: License :: OSI Approved :: Mozilla Public License 2.0 (MPL 2.0)
Classifier: Operating System :: OS Independent
Classifier: Framework :: Django
Classifier: Development Status :: 5 - Production/Stable
Requires-Python: >=3.6
License-File: LICENSE
Requires-Dist: pyrsistent >=0.16.1
